CHANGES.txt
MANIFEST.in
README.rst
setup.py
isotoma/__init__.py
isotoma.recipe.zope2instance.egg-info/PKG-INFO
isotoma.recipe.zope2instance.egg-info/SOURCES.txt
isotoma.recipe.zope2instance.egg-info/dependency_links.txt
isotoma.recipe.zope2instance.egg-info/entry_points.txt
isotoma.recipe.zope2instance.egg-info/namespace_packages.txt
isotoma.recipe.zope2instance.egg-info/not-zip-safe
isotoma.recipe.zope2instance.egg-info/requires.txt
isotoma.recipe.zope2instance.egg-info/top_level.txt
isotoma/recipe/__init__.py
isotoma/recipe/zope2instance/__init__.py
isotoma/recipe/zope2instance/ctl.py
isotoma/recipe/zope2instance/filestorage.py
isotoma/recipe/zope2instance/tests/__init__.py
isotoma/recipe/zope2instance/tests/test_docs.py