Metadata-Version: 1.0
Name: isotoma.recipe.zope2instance
Version: 0.0.3
Summary: Buildout recipes for create zope2instances
Home-page: http://pypi.python.org/pypi/isotoma.recipe.zope2instance
Author: John Carr
Author-email: john.carr@isotoma.com
License: Apache Software License
Keywords: buildout cron
Platform: UNKNOWN
Classifier: Framework :: Buildout
Classifier: Intended Audience :: System Administrators
Classifier: Operating System :: POSIX
Classifier: License :: OSI Approved :: Zope Public License
